odoo/addons/base_user_role_profile_example/README.rst
odoo/addons/base_user_role_profile_example/__init__.py
odoo/addons/base_user_role_profile_example/__manifest__.py
odoo/addons/base_user_role_profile_example/demo/demo.xml
odoo/addons/base_user_role_profile_example/i18n/base_user_role_profile_example.pot
odoo/addons/base_user_role_profile_example/readme/CONFIGURE.rst
odoo/addons/base_user_role_profile_example/readme/CONTRIBUTORS.rst
odoo/addons/base_user_role_profile_example/readme/DESCRIPTION.rst
odoo/addons/base_user_role_profile_example/readme/USAGE.rst
odoo/addons/base_user_role_profile_example/static/description/icon.png
odoo/addons/base_user_role_profile_example/static/description/index.html
odoo12_addon_base_user_role_profile_example-12.0.1.0.0.99.dev5.dist-info/METADATA
odoo12_addon_base_user_role_profile_example-12.0.1.0.0.99.dev5.dist-info/WHEEL
odoo12_addon_base_user_role_profile_example-12.0.1.0.0.99.dev5.dist-info/top_level.txt
odoo12_addon_base_user_role_profile_example-12.0.1.0.0.99.dev5.dist-info/RECORD
